statsbomb/__init__.py
statsbomb/base.py
statsbomb/events.yaml
statsbomb/parser.py
statsbomb/utils.py
statsbomb-0.3.0.dist-info/LICENSE
statsbomb-0.3.0.dist-info/METADATA
statsbomb-0.3.0.dist-info/WHEEL
statsbomb-0.3.0.dist-info/top_level.txt
statsbomb-0.3.0.dist-info/RECORD
