Metadata-Version: 2.1
Name: statsbomb
Version: 0.3.0
Summary: A Python package to parse StatsBomb JSON data to CSV
Home-page: https://github.com/imrankhan17/statsbomb-parser
Author: Imran Khan
Author-email: imrankhan17@hotmail.co.uk
License: MIT
Platform: UNKNOWN
Classifier: Programming Language :: Python :: 3
Classifier: License :: OSI Approved :: MIT License
Classifier: Operating System :: OS Independent
Requires-Dist: pandas
Requires-Dist: PyYAML
Requires-Dist: requests
